GreekRomanUtils/GreekRoman.py
GreekRomanUtils/__init__.py
GreekRomanUtils/DataStorage/Alphabet.py
GreekRomanUtils/DataStorage/__init__.py
GreekRomanUtils/DataType/GreekRomanType.py
GreekRomanUtils/DataType/__init__.py
greekromanutils-1.0.6.dist-info/METADATA
greekromanutils-1.0.6.dist-info/WHEEL
greekromanutils-1.0.6.dist-info/licenses/LICENSE
greekromanutils-1.0.6.dist-info/RECORD
