Metadata-Version: 2.4
Name: GreekRomanUtils
Version: 1.0.6
Summary: The module converts Arabic numerals to Greek and Roman numbers
Project-URL: Homepage, https://github.com/PavelKotDRM/GreekRomanNumerical
Project-URL: Documentation, https://github.com/PavelKotDRM/GreekRomanNumerical
Author-email: PKALab <kpalab@pkotlyarov.ru>
License: Apache-2.0
License-File: LICENSE
Keywords: greek,python,roman
Classifier: License :: OSI Approved :: Apache Software License
Classifier: Programming Language :: Python :: 3.11
Classifier: Programming Language :: Python :: 3.12
Classifier: Programming Language :: Python :: 3.13
Classifier: Programming Language :: Python :: 3.14
Classifier: Programming Language :: Python :: 3.15
Requires-Python: >=3.11
